<!--
  Policy APIM — POST /api/payments
  Appelle la Function fraud-check avant de router vers le backend payment.
  Si deny → 403 Forbidden. Si allow → forward au backend.
  Named Value requise : {{fraud-check-url}}
-->
<policies>
  <inbound>
    <base />

    <!-- Étape 1 : Construire le payload pour la Function fraud-check -->
    <set-variable name="clientIp"
                  value="@(context.Request.IpAddress)" />

    <set-variable name="paymentBody"
                  value="@(context.Request.Body.As&lt;string&gt;(preserveContent: true))" />

    <set-variable name="fraudCheckPayload" value="@{
      var body = Newtonsoft.Json.Linq.JObject.Parse(
        (string)context.Variables[&quot;paymentBody&quot;]
      );
      body[&quot;client_ip&quot;] = (string)context.Variables[&quot;clientIp&quot;];
      body[&quot;user_id&quot;] = context.Request.Headers.GetValueOrDefault(&quot;X-User-ID&quot;, &quot;anonymous&quot;);
      return body.ToString(Newtonsoft.Json.Formatting.None);
    }" />

    <!-- Étape 2 : Appel synchrone à la Function fraud-check -->
    <send-request mode="new"
                  response-variable-name="fraudCheckResponse"
                  timeout="10"
                  ignore-error="false">
      <set-url>{{fraud-check-url}}</set-url>
      <set-method>POST</set-method>
      <set-header name="Content-Type" exists-action="override">
        <value>application/json</value>
      </set-header>
      <set-body>@((string)context.Variables["fraudCheckPayload"])</set-body>
    </send-request>

    <!-- Étape 3 : Lire la décision retournée par la Function -->
    <set-variable name="fraudResponseBody" value="@{
      var response = (IResponse)context.Variables[&quot;fraudCheckResponse&quot;];
      return response.Body.As&lt;string&gt;();
    }" />

    <set-variable name="fraudDecision" value="@{
      var json = Newtonsoft.Json.Linq.JObject.Parse(
        (string)context.Variables[&quot;fraudResponseBody&quot;]
      );
      return json[&quot;decision&quot;]?.ToString() ?? &quot;deny&quot;;
    }" />

    <set-variable name="fraudReason" value="@{
      var json = Newtonsoft.Json.Linq.JObject.Parse(
        (string)context.Variables[&quot;fraudResponseBody&quot;]
      );
      return json[&quot;reason&quot;]?.ToString() ?? &quot;unknown&quot;;
    }" />

    <!-- Étape 4 : Bloquer si deny -->
    <choose>
      <when condition="@((string)context.Variables[&quot;fraudDecision&quot;] == &quot;deny&quot;)">
        <return-response>
          <set-status code="403" reason="Forbidden" />
          <set-header name="Content-Type" exists-action="override">
            <value>application/json</value>
          </set-header>
          <set-header name="Access-Control-Allow-Origin" exists-action="override">
            <value>@(context.Request.Headers.GetValueOrDefault("Origin",""))</value>
          </set-header>
          <set-header name="Access-Control-Allow-Credentials" exists-action="override">
            <value>true</value>
          </set-header>
          <set-body>@{
            return Newtonsoft.Json.JsonConvert.SerializeObject(new {
              error   = "payment_blocked",
              message = "Payment rejected by fraud detection.",
              reason  = (string)context.Variables["fraudReason"]
            });
          }</set-body>
        </return-response>
      </when>
    </choose>
  </inbound>

  <backend>
    <base />
  </backend>

  <outbound>
    <base />
  </outbound>

  <on-error>
    <base />
    <choose>
      <when condition="@(context.LastError.Source == &quot;send-request&quot;)">
        <return-response>
          <set-status code="503" reason="Service Unavailable" />
          <set-header name="Content-Type" exists-action="override">
            <value>application/json</value>
          </set-header>
          <set-header name="Access-Control-Allow-Origin" exists-action="override">
            <value>@(context.Request.Headers.GetValueOrDefault("Origin",""))</value>
          </set-header>
          <set-header name="Access-Control-Allow-Credentials" exists-action="override">
            <value>true</value>
          </set-header>
          <set-body>@{
            return Newtonsoft.Json.JsonConvert.SerializeObject(new {
              error   = "fraud_check_unavailable",
              message = "Payment temporarily unavailable. Please retry."
            });
          }</set-body>
        </return-response>
      </when>
    </choose>
  </on-error>
</policies>
